<?xml version="1.0" encoding="utf-8"?><toc><breadcrumbs><li><a href="G_ProjectLCore.htm">Docs</a></li><li><a href="G_ProjectLCore.htm">Project<wbr />LCore Namespaces</a></li><li><a href="N_ProjectLCore_GameActions.htm">Project<wbr />LCore.<wbr />Game<wbr />Actions</a></li></breadcrumbs><tocItems><li><a id="T_ProjectLCore_GameActions_ActionStatus" href="T_ProjectLCore_GameActions_ActionStatus.htm">Action<wbr />Status</a></li><li><a id="T_ProjectLCore_GameActions_ActionVerifier" class="has-submenu" href="T_ProjectLCore_GameActions_ActionVerifier.htm"><span data-tocFile="../toc/IDBBA.xml" class="icon toggle" onclick="ToggleExpandCollapse(this); return false;"><i class="fa fa-angle-right"> </i></span>Action<wbr />Verifier</a><ul class="toc-menu is-hidden"> </ul></li><li><a id="T_ProjectLCore_GameActions_CannotPlaceTetrominoFail" class="has-submenu" href="T_ProjectLCore_GameActions_CannotPlaceTetrominoFail.htm"><span data-tocFile="../toc/IDCBA.xml" class="icon toggle" onclick="ToggleExpandCollapse(this); return false;"><i class="fa fa-angle-right"> </i></span>Cannot<wbr />Place<wbr />Tetromino<wbr />Fail</a><ul class="toc-menu is-hidden"> </ul></li><li><a id="T_ProjectLCore_GameActions_DoNothingAction" class="has-submenu" href="T_ProjectLCore_GameActions_DoNothingAction.htm"><span data-tocFile="../toc/IDDBA.xml" class="icon toggle" onclick="ToggleExpandCollapse(this); return false;"><i class="fa fa-angle-right"> </i></span>Do<wbr />Nothing<wbr />Action</a><ul class="toc-menu is-hidden"> </ul></li><li><a id="T_ProjectLCore_GameActions_EmptyRowRecycleFail" class="has-submenu" href="T_ProjectLCore_GameActions_EmptyRowRecycleFail.htm"><span data-tocFile="../toc/IDEBA.xml" class="icon toggle" onclick="ToggleExpandCollapse(this); return false;"><i class="fa fa-angle-right"> </i></span>Empty<wbr />Row<wbr />Recycle<wbr />Fail</a><ul class="toc-menu is-hidden"> </ul></li><li><a id="T_ProjectLCore_GameActions_EndFinishingTouchesAction" class="has-submenu" href="T_ProjectLCore_GameActions_EndFinishingTouchesAction.htm"><span data-tocFile="../toc/IDFBA.xml" class="icon toggle" onclick="ToggleExpandCollapse(this); return false;"><i class="fa fa-angle-right"> </i></span>End<wbr />Finishing<wbr />Touches<wbr />Action</a><ul class="toc-menu is-hidden"> </ul></li><li><a id="T_ProjectLCore_GameActions_GameActionProcessor" class="has-submenu" href="T_ProjectLCore_GameActions_GameActionProcessor.htm"><span data-tocFile="../toc/IDGBA.xml" class="icon toggle" onclick="ToggleExpandCollapse(this); return false;"><i class="fa fa-angle-right"> </i></span>Game<wbr />Action<wbr />Processor</a><ul class="toc-menu is-hidden"> </ul></li><li><a id="T_ProjectLCore_GameActions_ChangeTetrominoAction" class="has-submenu" href="T_ProjectLCore_GameActions_ChangeTetrominoAction.htm"><span data-tocFile="../toc/IDHBA.xml" class="icon toggle" onclick="ToggleExpandCollapse(this); return false;"><i class="fa fa-angle-right"> </i></span>Change<wbr />Tetromino<wbr />Action</a><ul class="toc-menu is-hidden"> </ul></li><li><a id="T_ProjectLCore_GameActions_IAction" class="has-submenu" href="T_ProjectLCore_GameActions_IAction.htm"><span data-tocFile="../toc/IDIBA.xml" class="icon toggle" onclick="ToggleExpandCollapse(this); return false;"><i class="fa fa-angle-right"> </i></span>IAction</a><ul class="toc-menu is-hidden"> </ul></li><li><a id="T_ProjectLCore_GameActions_IActionProcessor" class="has-submenu" href="T_ProjectLCore_GameActions_IActionProcessor.htm"><span data-tocFile="../toc/IDJBA.xml" class="icon toggle" onclick="ToggleExpandCollapse(this); return false;"><i class="fa fa-angle-right"> </i></span>IAction<wbr />Processor</a><ul class="toc-menu is-hidden"> </ul></li><li><a id="T_ProjectLCore_GameActions_InvalidActionDuringFinishingTouchesFail" class="has-submenu" href="T_ProjectLCore_GameActions_InvalidActionDuringFinishingTouchesFail.htm"><span data-tocFile="../toc/IDKBA.xml" class="icon toggle" onclick="ToggleExpandCollapse(this); return false;"><i class="fa fa-angle-right"> </i></span>Invalid<wbr />Action<wbr />During<wbr />Finishing<wbr />Touches<wbr />Fail</a><ul class="toc-menu is-hidden"> </ul></li><li><a id="T_ProjectLCore_GameActions_InvalidEndFinishingTouchesActionUseFail" class="has-submenu" href="T_ProjectLCore_GameActions_InvalidEndFinishingTouchesActionUseFail.htm"><span data-tocFile="../toc/IDLBA.xml" class="icon toggle" onclick="ToggleExpandCollapse(this); return false;"><i class="fa fa-angle-right"> </i></span>Invalid<wbr />End<wbr />Finishing<wbr />Touches<wbr />Action<wbr />Use<wbr />Fail</a><ul class="toc-menu is-hidden"> </ul></li><li><a id="T_ProjectLCore_GameActions_InvalidTetrominoConfigurationFail" class="has-submenu" href="T_ProjectLCore_GameActions_InvalidTetrominoConfigurationFail.htm"><span data-tocFile="../toc/IDMBA.xml" class="icon toggle" onclick="ToggleExpandCollapse(this); return false;"><i class="fa fa-angle-right"> </i></span>Invalid<wbr />Tetromino<wbr />Configuration<wbr />Fail</a><ul class="toc-menu is-hidden"> </ul></li><li><a id="T_ProjectLCore_GameActions_InvalidTetrominoChangeFail" class="has-submenu" href="T_ProjectLCore_GameActions_InvalidTetrominoChangeFail.htm"><span data-tocFile="../toc/IDNBA.xml" class="icon toggle" onclick="ToggleExpandCollapse(this); return false;"><i class="fa fa-angle-right"> </i></span>Invalid<wbr />Tetromino<wbr />Change<wbr />Fail</a><ul class="toc-menu is-hidden"> </ul></li><li><a id="T_ProjectLCore_GameActions_MasterAction" class="has-submenu" href="T_ProjectLCore_GameActions_MasterAction.htm"><span data-tocFile="../toc/IDOBA.xml" class="icon toggle" onclick="ToggleExpandCollapse(this); return false;"><i class="fa fa-angle-right"> </i></span>Master<wbr />Action</a><ul class="toc-menu is-hidden"> </ul></li><li><a id="T_ProjectLCore_GameActions_MasterActionAlreadyUsedFail" class="has-submenu" href="T_ProjectLCore_GameActions_MasterActionAlreadyUsedFail.htm"><span data-tocFile="../toc/IDPBA.xml" class="icon toggle" onclick="ToggleExpandCollapse(this); return false;"><i class="fa fa-angle-right"> </i></span>Master<wbr />Action<wbr />Already<wbr />Used<wbr />Fail</a><ul class="toc-menu is-hidden"> </ul></li><li><a id="T_ProjectLCore_GameActions_MasterActionNotEnoughTetrominosFail" class="has-submenu" href="T_ProjectLCore_GameActions_MasterActionNotEnoughTetrominosFail.htm"><span data-tocFile="../toc/IDQBA.xml" class="icon toggle" onclick="ToggleExpandCollapse(this); return false;"><i class="fa fa-angle-right"> </i></span>Master<wbr />Action<wbr />Not<wbr />Enough<wbr />Tetrominos<wbr />Fail</a><ul class="toc-menu is-hidden"> </ul></li><li><a id="T_ProjectLCore_GameActions_MasterActionUniquePlacementFail" class="has-submenu" href="T_ProjectLCore_GameActions_MasterActionUniquePlacementFail.htm"><span data-tocFile="../toc/IDRBA.xml" class="icon toggle" onclick="ToggleExpandCollapse(this); return false;"><i class="fa fa-angle-right"> </i></span>Master<wbr />Action<wbr />Unique<wbr />Placement<wbr />Fail</a><ul class="toc-menu is-hidden"> </ul></li><li><a id="T_ProjectLCore_GameActions_NumberOfRecycledPuzzlesMismatchFail" class="has-submenu" href="T_ProjectLCore_GameActions_NumberOfRecycledPuzzlesMismatchFail.htm"><span data-tocFile="../toc/IDSBA.xml" class="icon toggle" onclick="ToggleExpandCollapse(this); return false;"><i class="fa fa-angle-right"> </i></span>Number<wbr />Of<wbr />Recycled<wbr />Puzzles<wbr />Mismatch<wbr />Fail</a><ul class="toc-menu is-hidden"> </ul></li><li><a id="T_ProjectLCore_GameActions_PlaceTetrominoAction" class="has-submenu" href="T_ProjectLCore_GameActions_PlaceTetrominoAction.htm"><span data-tocFile="../toc/IDTBA.xml" class="icon toggle" onclick="ToggleExpandCollapse(this); return false;"><i class="fa fa-angle-right"> </i></span>Place<wbr />Tetromino<wbr />Action</a><ul class="toc-menu is-hidden"> </ul></li><li><a id="T_ProjectLCore_GameActions_PlayerAlreadyTookBlackPuzzleInEndOfTheGameFail" class="has-submenu" href="T_ProjectLCore_GameActions_PlayerAlreadyTookBlackPuzzleInEndOfTheGameFail.htm"><span data-tocFile="../toc/IDUBA.xml" class="icon toggle" onclick="ToggleExpandCollapse(this); return false;"><i class="fa fa-angle-right"> </i></span>Player<wbr />Already<wbr />Took<wbr />Black<wbr />Puzzle<wbr />In<wbr />End<wbr />Of<wbr />The<wbr />Game<wbr />Fail</a><ul class="toc-menu is-hidden"> </ul></li><li><a id="T_ProjectLCore_GameActions_PlayerDoesntHavePuzzleFail" class="has-submenu" href="T_ProjectLCore_GameActions_PlayerDoesntHavePuzzleFail.htm"><span data-tocFile="../toc/IDVBA.xml" class="icon toggle" onclick="ToggleExpandCollapse(this); return false;"><i class="fa fa-angle-right"> </i></span>Player<wbr />Doesnt<wbr />Have<wbr />Puzzle<wbr />Fail</a><ul class="toc-menu is-hidden"> </ul></li><li><a id="T_ProjectLCore_GameActions_PuzzleDeckIsEmptyFail" class="has-submenu" href="T_ProjectLCore_GameActions_PuzzleDeckIsEmptyFail.htm"><span data-tocFile="../toc/IDWBA.xml" class="icon toggle" onclick="ToggleExpandCollapse(this); return false;"><i class="fa fa-angle-right"> </i></span>Puzzle<wbr />Deck<wbr />Is<wbr />Empty<wbr />Fail</a><ul class="toc-menu is-hidden"> </ul></li><li><a id="T_ProjectLCore_GameActions_PuzzleIdIsNullFail" class="has-submenu" href="T_ProjectLCore_GameActions_PuzzleIdIsNullFail.htm"><span data-tocFile="../toc/IDXBA.xml" class="icon toggle" onclick="ToggleExpandCollapse(this); return false;"><i class="fa fa-angle-right"> </i></span>Puzzle<wbr />Id<wbr />Is<wbr />Null<wbr />Fail</a><ul class="toc-menu is-hidden"> </ul></li><li><a id="T_ProjectLCore_GameActions_PuzzleNotAvailableFail" class="has-submenu" href="T_ProjectLCore_GameActions_PuzzleNotAvailableFail.htm"><span data-tocFile="../toc/IDYBA.xml" class="icon toggle" onclick="ToggleExpandCollapse(this); return false;"><i class="fa fa-angle-right"> </i></span>Puzzle<wbr />Not<wbr />Available<wbr />Fail</a><ul class="toc-menu is-hidden"> </ul></li><li><a id="T_ProjectLCore_GameActions_PuzzleNotInRowFail" class="has-submenu" href="T_ProjectLCore_GameActions_PuzzleNotInRowFail.htm"><span data-tocFile="../toc/IDZBA.xml" class="icon toggle" onclick="ToggleExpandCollapse(this); return false;"><i class="fa fa-angle-right"> </i></span>Puzzle<wbr />Not<wbr />In<wbr />Row<wbr />Fail</a><ul class="toc-menu is-hidden"> </ul></li><li><a id="T_ProjectLCore_GameActions_RecycleAction" class="has-submenu" href="T_ProjectLCore_GameActions_RecycleAction.htm"><span data-tocFile="../toc/ID1BA.xml" class="icon toggle" onclick="ToggleExpandCollapse(this); return false;"><i class="fa fa-angle-right"> </i></span>Recycle<wbr />Action</a><ul class="toc-menu is-hidden"> </ul></li><li><a id="T_ProjectLCore_GameActions_RecycleAction_Options" href="T_ProjectLCore_GameActions_RecycleAction_Options.htm">Recycle<wbr />Action.<wbr />Options</a></li><li><a id="T_ProjectLCore_GameActions_TakeBasicTetrominoAction" class="has-submenu" href="T_ProjectLCore_GameActions_TakeBasicTetrominoAction.htm"><span data-tocFile="../toc/ID3BA.xml" class="icon toggle" onclick="ToggleExpandCollapse(this); return false;"><i class="fa fa-angle-right"> </i></span>Take<wbr />Basic<wbr />Tetromino<wbr />Action</a><ul class="toc-menu is-hidden"> </ul></li><li><a id="T_ProjectLCore_GameActions_TakePuzzleAction" class="has-submenu" href="T_ProjectLCore_GameActions_TakePuzzleAction.htm"><span data-tocFile="../toc/ID4BA.xml" class="icon toggle" onclick="ToggleExpandCollapse(this); return false;"><i class="fa fa-angle-right"> </i></span>Take<wbr />Puzzle<wbr />Action</a><ul class="toc-menu is-hidden"> </ul></li><li><a id="T_ProjectLCore_GameActions_TakePuzzleAction_Options" href="T_ProjectLCore_GameActions_TakePuzzleAction_Options.htm">Take<wbr />Puzzle<wbr />Action.<wbr />Options</a></li><li><a id="T_ProjectLCore_GameActions_TetrominoAction" class="has-submenu" href="T_ProjectLCore_GameActions_TetrominoAction.htm"><span data-tocFile="../toc/ID6BA.xml" class="icon toggle" onclick="ToggleExpandCollapse(this); return false;"><i class="fa fa-angle-right"> </i></span>Tetromino<wbr />Action</a><ul class="toc-menu is-hidden"> </ul></li><li><a id="T_ProjectLCore_GameActions_TetrominoNotInPersonalSupplyFail" class="has-submenu" href="T_ProjectLCore_GameActions_TetrominoNotInPersonalSupplyFail.htm"><span data-tocFile="../toc/ID0AB0BA.xml" class="icon toggle" onclick="ToggleExpandCollapse(this); return false;"><i class="fa fa-angle-right"> </i></span>Tetromino<wbr />Not<wbr />In<wbr />Personal<wbr />Supply<wbr />Fail</a><ul class="toc-menu is-hidden"> </ul></li><li><a id="T_ProjectLCore_GameActions_TetrominoNotInSharedReserveFail" class="has-submenu" href="T_ProjectLCore_GameActions_TetrominoNotInSharedReserveFail.htm"><span data-tocFile="../toc/ID0BB0BA.xml" class="icon toggle" onclick="ToggleExpandCollapse(this); return false;"><i class="fa fa-angle-right"> </i></span>Tetromino<wbr />Not<wbr />In<wbr />Shared<wbr />Reserve<wbr />Fail</a><ul class="toc-menu is-hidden"> </ul></li><li><a id="T_ProjectLCore_GameActions_VerifiableAction" class="has-submenu" href="T_ProjectLCore_GameActions_VerifiableAction.htm"><span data-tocFile="../toc/ID0CB0BA.xml" class="icon toggle" onclick="ToggleExpandCollapse(this); return false;"><i class="fa fa-angle-right"> </i></span>Verifiable<wbr />Action</a><ul class="toc-menu is-hidden"> </ul></li><li><a id="T_ProjectLCore_GameActions_VerificationFailure" class="has-submenu" href="T_ProjectLCore_GameActions_VerificationFailure.htm"><span data-tocFile="../toc/ID0DB0BA.xml" class="icon toggle" onclick="ToggleExpandCollapse(this); return false;"><i class="fa fa-angle-right"> </i></span>Verification<wbr />Failure</a><ul class="toc-menu is-hidden"> </ul></li><li><a id="T_ProjectLCore_GameActions_VerificationStatus" class="has-submenu" href="T_ProjectLCore_GameActions_VerificationStatus.htm"><span data-tocFile="../toc/ID0EB0BA.xml" class="icon toggle" onclick="ToggleExpandCollapse(this); return false;"><i class="fa fa-angle-right"> </i></span>Verification<wbr />Status</a><ul class="toc-menu is-hidden"> </ul></li><li><a id="T_ProjectLCore_GameActions_VerificationSuccess" class="has-submenu" href="T_ProjectLCore_GameActions_VerificationSuccess.htm"><span data-tocFile="../toc/ID0FB0BA.xml" class="icon toggle" onclick="ToggleExpandCollapse(this); return false;"><i class="fa fa-angle-right"> </i></span>Verification<wbr />Success</a><ul class="toc-menu is-hidden"> </ul></li></tocItems></toc>